{
  "pdf_path": "C:/Users/svarovsky/PycharmProjects/RD/АДМК21-ЭГ (от 20.08.2025).pdf",
  "pages": [
    {
      "page_index": 0,
      "width": 1786,
      "height": 2527,
      "blocks": [
        {
          "id": "3f99d60a-ca04-486b-9d9c-49a1d9eb5d3f",
          "page_index": 0,
          "coords_px": [
            211,
            541,
            1671,
            1810
          ],
          "coords_norm": [
            0.11820728291316526,
            0.21417260490894696,
            0.9361344537815126,
            0.716547901821061
          ],
          "category": "",
          "block_type": "text",
          "source": "user",
          "image_file": "page0_block3f99d60a-ca04-486b-9d9c-49a1d9eb5d3f.jpg",
          "ocr_text": null
        }
      ]
    },
    {
      "page_index": 1,
      "width": 1786,
      "height": 2527,
      "blocks": [
        {
          "id": "7751ed47-c649-4c1f-88f3-6efaa75ecca3",
          "page_index": 1,
          "coords_px": [
            211,
            577,
            1665,
            1665
          ],
          "coords_norm": [
            0.11820728291316526,
            0.22842438638163104,
            0.9327731092436975,
            0.6591448931116389
          ],
          "category": "",
          "block_type": "text",
          "source": "user",
          "image_file": "page1_block7751ed47-c649-4c1f-88f3-6efaa75ecca3.jpg",
          "ocr_text": null
        }
      ]
    },
    {
      "page_index": 2,
      "width": 1786,
      "height": 2527,
      "blocks": [
        {
          "id": "c15720b8-35e1-436d-a001-a42c5c9babe0",
          "page_index": 2,
          "coords_px": [
            215,
            567,
            1681,
            2031
          ],
          "coords_norm": [
            0.12044817927170869,
            0.22446555819477435,
            0.9417366946778711,
            0.8040380047505938
          ],
          "category": "",
          "block_type": "text",
          "source": "user",
          "image_file": "page2_blockc15720b8-35e1-436d-a001-a42c5c9babe0.jpg",
          "ocr_text": null
        }
      ]
    },
    {
      "page_index": 3,
      "width": 1786,
      "height": 2527,
      "blocks": []
    },
    {
      "page_index": 4,
      "width": 1785,
      "height": 2526,
      "blocks": []
    },
    {
      "page_index": 5,
      "width": 1785,
      "height": 2526,
      "blocks": []
    },
    {
      "page_index": 6,
      "width": 3573,
      "height": 2527,
      "blocks": [
        {
          "id": "53845f66-21ca-43ec-824c-9bb9904392bd",
          "page_index": 6,
          "coords_px": [
            1838,
            400,
            3509,
            1725
          ],
          "coords_norm": [
            0.5145576707726763,
            0.1583531274742676,
            0.9823628219484882,
            0.6828978622327792
          ],
          "category": "",
          "block_type": "table",
          "source": "user",
          "image_file": "page6_block53845f66-21ca-43ec-824c-9bb9904392bd.jpg",
          "ocr_text": null
        }
      ]
    }
  ]
}